{"header":"PROCESSED on Thu, 04 Dec 2025 14:49:16 +0000 from https:\/\/easyins.ru\/","files":{"clipboard":{"url":"\/wp-includes\/js\/clipboard.min.js","success":true,"uses_loading_strategy":false,"version":"2.0.11","last_modified":"1738862846"},"media-views":{"url":"\/wp-includes\/js\/media-views.min.js","success":true,"uses_loading_strategy":false,"version":false,"last_modified":"1742401648"},"media-editor":{"url":"\/wp-includes\/js\/media-editor.min.js","success":true,"uses_loading_strategy":false,"version":false,"last_modified":"1738862846"},"media-audiovideo":{"url":"\/wp-includes\/js\/media-audiovideo.min.js","success":true,"uses_loading_strategy":false,"version":false,"last_modified":"1741100129"}}}